{"maxConflicts": 100, "logPath": "../data/synthetic/2018-05-01_small/net3/net3-10-60.xes.gz", "log": "net3-10-60", "outFile": "../results/2018-05-12_03:14:26:046674_20180501_R_score_L_exclude_S_M15/results.csv", "nofIterations": 200, "alignmentPercentage": 100, "preferBorderTransitions": false, "intervalAbsolute": 0, "recomposeStrategy": "Score-based", "moveOnModelCosts": 4, "localDuration": 80000, "useHideAndReduceAbstraction": true, "iteration": 9, "moveOnLogCosts": 10, "globalDuration": 900000, "logCreationStrategy": "Strict exclude by conflicts", "model": "net3", "addConflictOnlyOnce": true, "modelPath": "../data/synthetic/2018-05-01_small/net3/net3.apnml", "initDecompFile": "../data/synthetic/2018-05-01_small/net3/decomposition/net3.sese_25", "intervalRelative": 100, "decomposition": "sese_25"}